{
  "Id": "02aa3e4c-0e7e-45b9-9bf6-e661a373adb2",
  "PlayersCount": 2,
  "InitialStack": 1000.0,
  "MaxRound": 100,
  "SmallBlind": 10.0,
  "BigBlind": 20.0,
  "Ante": 0.0,
  "Players": [
    {
      "Name": "Random",
      "Id": "nanlhrdqkzbzdgwizomihg"
    },
    {
      "Name": "PokerShark",
      "Id": "lzetymnatpektjoxdrmpaq"
    }
  ],
  "Rounds": [
    {
      "SmallBlindPosition": 1,
      "BigBlindPosition": 0,
      "Players": [
        {
          "Name": "Random",
          "Id": "nanlhrdqkzbzdgwizomihg",
          "Stack": 1010.0,
          "State": "Participating"
        },
        {
          "Name": "PokerShark",
          "Id": "lzetymnatpektjoxdrmpaq",
          "Stack": 990.0,
          "State": "Folded"
        }
      ],
      "RoundCount": 1,
      "Pocket": [
        "3D",
        "8D"
      ],
      "Pot": {
        "Amount": 30.0
      },
      "Winner": [
        {
          "Name": "Random",
          "Id": "nanlhrdqkzbzdgwizomihg",
          "Stack": 1010.0,
          "State": "Participating"
        }
      ],
      "History": [
        {
          "PlayerName": "PokerShark",
          "Stage": "Preflop",
          "Type": "Fold"
        }
      ],
      "OddsLog": []
    },
    {
      "SmallBlindPosition": 0,
      "BigBlindPosition": 1,
      "Players": [
        {
          "Name": "Random",
          "Id": "nanlhrdqkzbzdgwizomihg",
          "Stack": 1030.0,
          "State": "Participating"
        },
        {
          "Name": "PokerShark",
          "Id": "lzetymnatpektjoxdrmpaq",
          "Stack": 970.0,
          "State": "Folded"
        }
      ],
      "RoundCount": 2,
      "Pocket": [
        "4H",
        "TS"
      ],
      "Pot": {
        "Amount": 597.0
      },
      "Winner": [
        {
          "Name": "Random",
          "Id": "nanlhrdqkzbzdgwizomihg",
          "Stack": 1030.0,
          "State": "Participating"
        }
      ],
      "History": [
        {
          "PlayerName": "Random",
          "Amount": 577.0,
          "MinAmount": 577.0,
          "MaxAmount": 577.0,
          "Stage": "Preflop",
          "Type": "Raise"
        },
        {
          "PlayerName": "PokerShark",
          "Stage": "Preflop",
          "Type": "Fold"
        }
      ],
      "OddsLog": []
    },
    {
      "SmallBlindPosition": 1,
      "BigBlindPosition": 0,
      "Players": [
        {
          "Name": "Random",
          "Id": "nanlhrdqkzbzdgwizomihg",
          "Stack": 1040.0,
          "State": "Participating"
        },
        {
          "Name": "PokerShark",
          "Id": "lzetymnatpektjoxdrmpaq",
          "Stack": 960.0,
          "State": "Folded"
        }
      ],
      "RoundCount": 3,
      "Pocket": [
        "2D",
        "7D"
      ],
      "Pot": {
        "Amount": 30.0
      },
      "Winner": [
        {
          "Name": "Random",
          "Id": "nanlhrdqkzbzdgwizomihg",
          "Stack": 1040.0,
          "State": "Participating"
        }
      ],
      "History": [
        {
          "PlayerName": "PokerShark",
          "Stage": "Preflop",
          "Type": "Fold"
        }
      ],
      "OddsLog": []
    },
    {
      "SmallBlindPosition": 0,
      "BigBlindPosition": 1,
      "Players": [
        {
          "Name": "Random",
          "Id": "nanlhrdqkzbzdgwizomihg",
          "Stack": 1060.0,
          "State": "Participating"
        },
        {
          "Name": "PokerShark",
          "Id": "lzetymnatpektjoxdrmpaq",
          "Stack": 940.0,
          "State": "Folded"
        }
      ],
      "RoundCount": 4,
      "Pocket": [
        "KH",
        "QH"
      ],
      "Pot": {
        "Amount": 501.0
      },
      "Winner": [
        {
          "Name": "Random",
          "Id": "nanlhrdqkzbzdgwizomihg",
          "Stack": 1060.0,
          "State": "Participating"
        }
      ],
      "History": [
        {
          "PlayerName": "Random",
          "Amount": 481.0,
          "MinAmount": 481.0,
          "MaxAmount": 481.0,
          "Stage": "Preflop",
          "Type": "Raise"
        },
        {
          "PlayerName": "PokerShark",
          "Stage": "Preflop",
          "Type": "Fold"
        }
      ],
      "OddsLog": []
    },
    {
      "SmallBlindPosition": 1,
      "BigBlindPosition": 0,
      "Players": [
        {
          "Name": "Random",
          "Id": "nanlhrdqkzbzdgwizomihg",
          "Stack": 1070.0,
          "State": "Participating"
        },
        {
          "Name": "PokerShark",
          "Id": "lzetymnatpektjoxdrmpaq",
          "Stack": 930.0,
          "State": "Folded"
        }
      ],
      "RoundCount": 5,
      "Pocket": [
        "6D",
        "7H"
      ],
      "Pot": {
        "Amount": 30.0
      },
      "Winner": [
        {
          "Name": "Random",
          "Id": "nanlhrdqkzbzdgwizomihg",
          "Stack": 1070.0,
          "State": "Participating"
        }
      ],
      "History": [
        {
          "PlayerName": "PokerShark",
          "Stage": "Preflop",
          "Type": "Fold"
        }
      ],
      "OddsLog": []
    },
    {
      "SmallBlindPosition": 0,
      "BigBlindPosition": 1,
      "Players": [
        {
          "Name": "Random",
          "Id": "nanlhrdqkzbzdgwizomihg",
          "Stack": 1090.0,
          "State": "Participating"
        },
        {
          "Name": "PokerShark",
          "Id": "lzetymnatpektjoxdrmpaq",
          "Stack": 910.0,
          "State": "Folded"
        }
      ],
      "RoundCount": 6,
      "Pocket": [
        "7C",
        "KH"
      ],
      "Pot": {
        "Amount": 446.0
      },
      "Winner": [
        {
          "Name": "Random",
          "Id": "nanlhrdqkzbzdgwizomihg",
          "Stack": 1090.0,
          "State": "Participating"
        }
      ],
      "History": [
        {
          "PlayerName": "Random",
          "Amount": 426.0,
          "MinAmount": 426.0,
          "MaxAmount": 426.0,
          "Stage": "Preflop",
          "Type": "Raise"
        },
        {
          "PlayerName": "PokerShark",
          "Stage": "Preflop",
          "Type": "Fold"
        }
      ],
      "OddsLog": []
    },
    {
      "SmallBlindPosition": 1,
      "BigBlindPosition": 0,
      "Players": [
        {
          "Name": "Random",
          "Id": "nanlhrdqkzbzdgwizomihg",
          "Stack": 1100.0,
          "State": "Participating"
        },
        {
          "Name": "PokerShark",
          "Id": "lzetymnatpektjoxdrmpaq",
          "Stack": 900.0,
          "State": "Folded"
        }
      ],
      "RoundCount": 7,
      "Pocket": [
        "JH",
        "4C"
      ],
      "Pot": {
        "Amount": 30.0
      },
      "Winner": [
        {
          "Name": "Random",
          "Id": "nanlhrdqkzbzdgwizomihg",
          "Stack": 1100.0,
          "State": "Participating"
        }
      ],
      "History": [
        {
          "PlayerName": "PokerShark",
          "Stage": "Preflop",
          "Type": "Fold"
        }
      ],
      "OddsLog": []
    },
    {
      "SmallBlindPosition": 0,
      "BigBlindPosition": 1,
      "Players": [
        {
          "Name": "Random",
          "Id": "nanlhrdqkzbzdgwizomihg",
          "Stack": 1120.0,
          "State": "Participating"
        },
        {
          "Name": "PokerShark",
          "Id": "lzetymnatpektjoxdrmpaq",
          "Stack": 880.0,
          "State": "Folded"
        }
      ],
      "RoundCount": 8,
      "Pocket": [
        "2S",
        "8S"
      ],
      "Pot": {
        "Amount": 474.0
      },
      "Winner": [
        {
          "Name": "Random",
          "Id": "nanlhrdqkzbzdgwizomihg",
          "Stack": 1120.0,
          "State": "Participating"
        }
      ],
      "History": [
        {
          "PlayerName": "Random",
          "Amount": 454.0,
          "MinAmount": 454.0,
          "MaxAmount": 454.0,
          "Stage": "Preflop",
          "Type": "Raise"
        },
        {
          "PlayerName": "PokerShark",
          "Stage": "Preflop",
          "Type": "Fold"
        }
      ],
      "OddsLog": []
    },
    {
      "SmallBlindPosition": 1,
      "BigBlindPosition": 0,
      "Players": [
        {
          "Name": "Random",
          "Id": "nanlhrdqkzbzdgwizomihg",
          "Stack": 1130.0,
          "State": "Participating"
        },
        {
          "Name": "PokerShark",
          "Id": "lzetymnatpektjoxdrmpaq",
          "Stack": 870.0,
          "State": "Folded"
        }
      ],
      "RoundCount": 9,
      "Pocket": [
        "3D",
        "7H"
      ],
      "Pot": {
        "Amount": 30.0
      },
      "Winner": [
        {
          "Name": "Random",
          "Id": "nanlhrdqkzbzdgwizomihg",
          "Stack": 1130.0,
          "State": "Participating"
        }
      ],
      "History": [
        {
          "PlayerName": "PokerShark",
          "Stage": "Preflop",
          "Type": "Fold"
        }
      ],
      "OddsLog": []
    },
    {
      "SmallBlindPosition": 0,
      "BigBlindPosition": 1,
      "Players": [
        {
          "Name": "Random",
          "Id": "nanlhrdqkzbzdgwizomihg",
          "Stack": 1150.0,
          "State": "Participating"
        },
        {
          "Name": "PokerShark",
          "Id": "lzetymnatpektjoxdrmpaq",
          "Stack": 850.0,
          "State": "Folded"
        }
      ],
      "RoundCount": 10,
      "Pocket": [
        "QH",
        "4S"
      ],
      "Pot": {
        "Amount": 951.0
      },
      "Winner": [
        {
          "Name": "Random",
          "Id": "nanlhrdqkzbzdgwizomihg",
          "Stack": 1150.0,
          "State": "Participating"
        }
      ],
      "History": [
        {
          "PlayerName": "Random",
          "Amount": 931.0,
          "MinAmount": 931.0,
          "MaxAmount": 931.0,
          "Stage": "Preflop",
          "Type": "Raise"
        },
        {
          "PlayerName": "PokerShark",
          "Stage": "Preflop",
          "Type": "Fold"
        }
      ],
      "OddsLog": []
    },
    {
      "SmallBlindPosition": 1,
      "BigBlindPosition": 0,
      "Players": [
        {
          "Name": "Random",
          "Id": "nanlhrdqkzbzdgwizomihg",
          "Stack": 1130.0,
          "State": "Folded"
        },
        {
          "Name": "PokerShark",
          "Id": "lzetymnatpektjoxdrmpaq",
          "Stack": 870.0,
          "State": "Participating"
        }
      ],
      "RoundCount": 11,
      "Pocket": [
        "5S",
        "AS"
      ],
      "Pot": {
        "Amount": 50.0
      },
      "Winner": [
        {
          "Name": "PokerShark",
          "Id": "lzetymnatpektjoxdrmpaq",
          "Stack": 870.0,
          "State": "Participating"
        }
      ],
      "History": [
        {
          "PlayerName": "PokerShark",
          "Amount": 30.0,
          "MinAmount": 30.0,
          "MaxAmount": 30.0,
          "Stage": "Preflop",
          "Type": "Raise"
        },
        {
          "PlayerName": "Random",
          "Stage": "Preflop",
          "Type": "Fold"
        }
      ],
      "OddsLog": []
    },
    {
      "SmallBlindPosition": 0,
      "BigBlindPosition": 1,
      "Players": [
        {
          "Name": "Random",
          "Id": "nanlhrdqkzbzdgwizomihg",
          "Stack": 1150.0,
          "State": "Participating"
        },
        {
          "Name": "PokerShark",
          "Id": "lzetymnatpektjoxdrmpaq",
          "Stack": 850.0,
          "State": "Folded"
        }
      ],
      "RoundCount": 12,
      "Pocket": [
        "QC",
        "TS"
      ],
      "Pot": {
        "Amount": 905.0
      },
      "Winner": [
        {
          "Name": "Random",
          "Id": "nanlhrdqkzbzdgwizomihg",
          "Stack": 1150.0,
          "State": "Participating"
        }
      ],
      "History": [
        {
          "PlayerName": "Random",
          "Amount": 885.0,
          "MinAmount": 885.0,
          "MaxAmount": 885.0,
          "Stage": "Preflop",
          "Type": "Raise"
        },
        {
          "PlayerName": "PokerShark",
          "Stage": "Preflop",
          "Type": "Fold"
        }
      ],
      "OddsLog": []
    },
    {
      "SmallBlindPosition": 1,
      "BigBlindPosition": 0,
      "Players": [
        {
          "Name": "Random",
          "Id": "nanlhrdqkzbzdgwizomihg",
          "Stack": 1160.0,
          "State": "Participating"
        },
        {
          "Name": "PokerShark",
          "Id": "lzetymnatpektjoxdrmpaq",
          "Stack": 840.0,
          "State": "Folded"
        }
      ],
      "RoundCount": 13,
      "Pocket": [
        "8H",
        "7S"
      ],
      "Pot": {
        "Amount": 30.0
      },
      "Winner": [
        {
          "Name": "Random",
          "Id": "nanlhrdqkzbzdgwizomihg",
          "Stack": 1160.0,
          "State": "Participating"
        }
      ],
      "History": [
        {
          "PlayerName": "PokerShark",
          "Stage": "Preflop",
          "Type": "Fold"
        }
      ],
      "OddsLog": []
    },
    {
      "SmallBlindPosition": 0,
      "BigBlindPosition": 1,
      "Players": [
        {
          "Name": "Random",
          "Id": "nanlhrdqkzbzdgwizomihg",
          "Stack": 1180.0,
          "State": "Participating"
        },
        {
          "Name": "PokerShark",
          "Id": "lzetymnatpektjoxdrmpaq",
          "Stack": 820.0,
          "State": "Folded"
        }
      ],
      "RoundCount": 14,
      "Pocket": [
        "8H",
        "QH"
      ],
      "Pot": {
        "Amount": 518.0
      },
      "Winner": [
        {
          "Name": "Random",
          "Id": "nanlhrdqkzbzdgwizomihg",
          "Stack": 1180.0,
          "State": "Participating"
        }
      ],
      "History": [
        {
          "PlayerName": "Random",
          "Amount": 498.0,
          "MinAmount": 498.0,
          "MaxAmount": 498.0,
          "Stage": "Preflop",
          "Type": "Raise"
        },
        {
          "PlayerName": "PokerShark",
          "Stage": "Preflop",
          "Type": "Fold"
        }
      ],
      "OddsLog": []
    },
    {
      "SmallBlindPosition": 1,
      "BigBlindPosition": 0,
      "Players": [
        {
          "Name": "Random",
          "Id": "nanlhrdqkzbzdgwizomihg",
          "Stack": 1190.0,
          "State": "Participating"
        },
        {
          "Name": "PokerShark",
          "Id": "lzetymnatpektjoxdrmpaq",
          "Stack": 810.0,
          "State": "Folded"
        }
      ],
      "RoundCount": 15,
      "Pocket": [
        "TD",
        "4H"
      ],
      "Pot": {
        "Amount": 30.0
      },
      "Winner": [
        {
          "Name": "Random",
          "Id": "nanlhrdqkzbzdgwizomihg",
          "Stack": 1190.0,
          "State": "Participating"
        }
      ],
      "History": [
        {
          "PlayerName": "PokerShark",
          "Stage": "Preflop",
          "Type": "Fold"
        }
      ],
      "OddsLog": []
    },
    {
      "SmallBlindPosition": 0,
      "BigBlindPosition": 1,
      "Players": [
        {
          "Name": "Random",
          "Id": "nanlhrdqkzbzdgwizomihg",
          "Stack": 1180.0,
          "State": "Folded"
        },
        {
          "Name": "PokerShark",
          "Id": "lzetymnatpektjoxdrmpaq",
          "Stack": 820.0,
          "State": "Participating"
        }
      ],
      "RoundCount": 16,
      "Pocket": [
        "6D",
        "7D"
      ],
      "Pot": {
        "Amount": 30.0
      },
      "Winner": [
        {
          "Name": "PokerShark",
          "Id": "lzetymnatpektjoxdrmpaq",
          "Stack": 820.0,
          "State": "Participating"
        }
      ],
      "History": [
        {
          "PlayerName": "Random",
          "Stage": "Preflop",
          "Type": "Fold"
        }
      ],
      "OddsLog": []
    },
    {
      "SmallBlindPosition": 1,
      "BigBlindPosition": 0,
      "Players": [
        {
          "Name": "Random",
          "Id": "nanlhrdqkzbzdgwizomihg",
          "Stack": 1190.0,
          "State": "Participating"
        },
        {
          "Name": "PokerShark",
          "Id": "lzetymnatpektjoxdrmpaq",
          "Stack": 810.0,
          "State": "Folded"
        }
      ],
      "RoundCount": 17,
      "Pocket": [
        "3C",
        "TH"
      ],
      "Pot": {
        "Amount": 30.0
      },
      "Winner": [
        {
          "Name": "Random",
          "Id": "nanlhrdqkzbzdgwizomihg",
          "Stack": 1190.0,
          "State": "Participating"
        }
      ],
      "History": [
        {
          "PlayerName": "PokerShark",
          "Stage": "Preflop",
          "Type": "Fold"
        }
      ],
      "OddsLog": []
    },
    {
      "SmallBlindPosition": 0,
      "BigBlindPosition": 1,
      "Players": [
        {
          "Name": "Random",
          "Id": "nanlhrdqkzbzdgwizomihg",
          "Stack": 1180.0,
          "State": "Folded"
        },
        {
          "Name": "PokerShark",
          "Id": "lzetymnatpektjoxdrmpaq",
          "Stack": 820.0,
          "State": "Participating"
        }
      ],
      "RoundCount": 18,
      "Pocket": [
        "6C",
        "6D"
      ],
      "Pot": {
        "Amount": 30.0
      },
      "Winner": [
        {
          "Name": "PokerShark",
          "Id": "lzetymnatpektjoxdrmpaq",
          "Stack": 820.0,
          "State": "Participating"
        }
      ],
      "History": [
        {
          "PlayerName": "Random",
          "Stage": "Preflop",
          "Type": "Fold"
        }
      ],
      "OddsLog": []
    },
    {
      "SmallBlindPosition": 1,
      "BigBlindPosition": 0,
      "Players": [
        {
          "Name": "Random",
          "Id": "nanlhrdqkzbzdgwizomihg",
          "Stack": 1200.0,
          "State": "Participating"
        },
        {
          "Name": "PokerShark",
          "Id": "lzetymnatpektjoxdrmpaq",
          "Stack": 800.0,
          "State": "Folded"
        }
      ],
      "RoundCount": 19,
      "Pocket": [
        "3H",
        "TH"
      ],
      "Pot": {
        "Amount": 865.0
      },
      "Winner": [
        {
          "Name": "Random",
          "Id": "nanlhrdqkzbzdgwizomihg",
          "Stack": 1200.0,
          "State": "Participating"
        }
      ],
      "History": [
        {
          "PlayerName": "PokerShark",
          "Amount": 20.0,
          "Stage": "Preflop",
          "Type": "Call"
        },
        {
          "PlayerName": "Random",
          "Amount": 845.0,
          "MinAmount": 845.0,
          "MaxAmount": 845.0,
          "Stage": "Preflop",
          "Type": "Raise"
        },
        {
          "PlayerName": "PokerShark",
          "Stage": "Preflop",
          "Type": "Fold"
        }
      ],
      "OddsLog": []
    },
    {
      "SmallBlindPosition": 0,
      "BigBlindPosition": 1,
      "Players": [
        {
          "Name": "Random",
          "Id": "nanlhrdqkzbzdgwizomihg",
          "Stack": 1220.0,
          "State": "Participating"
        },
        {
          "Name": "PokerShark",
          "Id": "lzetymnatpektjoxdrmpaq",
          "Stack": 780.0,
          "State": "Folded"
        }
      ],
      "RoundCount": 20,
      "Pocket": [
        "7S",
        "AS"
      ],
      "Pot": {
        "Amount": 924.0
      },
      "Winner": [
        {
          "Name": "Random",
          "Id": "nanlhrdqkzbzdgwizomihg",
          "Stack": 1220.0,
          "State": "Participating"
        }
      ],
      "History": [
        {
          "PlayerName": "Random",
          "Amount": 904.0,
          "MinAmount": 904.0,
          "MaxAmount": 904.0,
          "Stage": "Preflop",
          "Type": "Raise"
        },
        {
          "PlayerName": "PokerShark",
          "Stage": "Preflop",
          "Type": "Fold"
        }
      ],
      "OddsLog": []
    },
    {
      "SmallBlindPosition": 1,
      "BigBlindPosition": 0,
      "Players": [
        {
          "Name": "Random",
          "Id": "nanlhrdqkzbzdgwizomihg",
          "Stack": 1240.0,
          "State": "Participating"
        },
        {
          "Name": "PokerShark",
          "Id": "lzetymnatpektjoxdrmpaq",
          "Stack": 760.0,
          "State": "Folded"
        }
      ],
      "RoundCount": 21,
      "Pocket": [
        "5H",
        "TH"
      ],
      "Pot": {
        "Amount": 263.0
      },
      "Winner": [
        {
          "Name": "Random",
          "Id": "nanlhrdqkzbzdgwizomihg",
          "Stack": 1240.0,
          "State": "Participating"
        }
      ],
      "History": [
        {
          "PlayerName": "PokerShark",
          "Amount": 20.0,
          "Stage": "Preflop",
          "Type": "Call"
        },
        {
          "PlayerName": "Random",
          "Amount": 243.0,
          "MinAmount": 243.0,
          "MaxAmount": 243.0,
          "Stage": "Preflop",
          "Type": "Raise"
        },
        {
          "PlayerName": "PokerShark",
          "Stage": "Preflop",
          "Type": "Fold"
        }
      ],
      "OddsLog": []
    },
    {
      "SmallBlindPosition": 0,
      "BigBlindPosition": 1,
      "Players": [
        {
          "Name": "Random",
          "Id": "nanlhrdqkzbzdgwizomihg",
          "Stack": 1230.0,
          "State": "Folded"
        },
        {
          "Name": "PokerShark",
          "Id": "lzetymnatpektjoxdrmpaq",
          "Stack": 770.0,
          "State": "Participating"
        }
      ],
      "RoundCount": 22,
      "Pocket": [
        "KC",
        "QC"
      ],
      "Pot": {
        "Amount": 30.0
      },
      "Winner": [
        {
          "Name": "PokerShark",
          "Id": "lzetymnatpektjoxdrmpaq",
          "Stack": 770.0,
          "State": "Participating"
        }
      ],
      "History": [
        {
          "PlayerName": "Random",
          "Stage": "Preflop",
          "Type": "Fold"
        }
      ],
      "OddsLog": []
    },
    {
      "SmallBlindPosition": 1,
      "BigBlindPosition": 0,
      "Players": [
        {
          "Name": "Random",
          "Id": "nanlhrdqkzbzdgwizomihg",
          "Stack": 1210.0,
          "State": "Folded"
        },
        {
          "Name": "PokerShark",
          "Id": "lzetymnatpektjoxdrmpaq",
          "Stack": 790.0,
          "State": "Participating"
        }
      ],
      "RoundCount": 23,
      "Pocket": [
        "KH",
        "3H"
      ],
      "Pot": {
        "Amount": 40.0
      },
      "Winner": [
        {
          "Name": "PokerShark",
          "Id": "lzetymnatpektjoxdrmpaq",
          "Stack": 790.0,
          "State": "Participating"
        }
      ],
      "History": [
        {
          "PlayerName": "PokerShark",
          "Amount": 20.0,
          "Stage": "Preflop",
          "Type": "Call"
        },
        {
          "PlayerName": "Random",
          "Stage": "Preflop",
          "Type": "Fold"
        }
      ],
      "OddsLog": []
    },
    {
      "SmallBlindPosition": 0,
      "BigBlindPosition": 1,
      "Players": [
        {
          "Name": "Random",
          "Id": "nanlhrdqkzbzdgwizomihg",
          "Stack": 1200.0,
          "State": "Folded"
        },
        {
          "Name": "PokerShark",
          "Id": "lzetymnatpektjoxdrmpaq",
          "Stack": 800.0,
          "State": "Participating"
        }
      ],
      "RoundCount": 24,
      "Pocket": [
        "JS",
        "3S"
      ],
      "Pot": {
        "Amount": 30.0
      },
      "Winner": [
        {
          "Name": "PokerShark",
          "Id": "lzetymnatpektjoxdrmpaq",
          "Stack": 800.0,
          "State": "Participating"
        }
      ],
      "History": [
        {
          "PlayerName": "Random",
          "Stage": "Preflop",
          "Type": "Fold"
        }
      ],
      "OddsLog": []
    },
    {
      "SmallBlindPosition": 1,
      "BigBlindPosition": 0,
      "Players": [
        {
          "Name": "Random",
          "Id": "nanlhrdqkzbzdgwizomihg",
          "Stack": 1210.0,
          "State": "Participating"
        },
        {
          "Name": "PokerShark",
          "Id": "lzetymnatpektjoxdrmpaq",
          "Stack": 790.0,
          "State": "Folded"
        }
      ],
      "RoundCount": 25,
      "Pocket": [
        "7H",
        "3H"
      ],
      "Pot": {
        "Amount": 30.0
      },
      "Winner": [
        {
          "Name": "Random",
          "Id": "nanlhrdqkzbzdgwizomihg",
          "Stack": 1210.0,
          "State": "Participating"
        }
      ],
      "History": [
        {
          "PlayerName": "PokerShark",
          "Stage": "Preflop",
          "Type": "Fold"
        }
      ],
      "OddsLog": []
    },
    {
      "SmallBlindPosition": 0,
      "BigBlindPosition": 1,
      "Players": [
        {
          "Name": "Random",
          "Id": "nanlhrdqkzbzdgwizomihg",
          "Stack": 1230.0,
          "State": "Participating"
        },
        {
          "Name": "PokerShark",
          "Id": "lzetymnatpektjoxdrmpaq",
          "Stack": 770.0,
          "State": "Folded"
        }
      ],
      "RoundCount": 26,
      "Pocket": [
        "TD",
        "6D"
      ],
      "Pot": {
        "Amount": 341.0
      },
      "Winner": [
        {
          "Name": "Random",
          "Id": "nanlhrdqkzbzdgwizomihg",
          "Stack": 1230.0,
          "State": "Participating"
        }
      ],
      "History": [
        {
          "PlayerName": "Random",
          "Amount": 321.0,
          "MinAmount": 321.0,
          "MaxAmount": 321.0,
          "Stage": "Preflop",
          "Type": "Raise"
        },
        {
          "PlayerName": "PokerShark",
          "Stage": "Preflop",
          "Type": "Fold"
        }
      ],
      "OddsLog": []
    },
    {
      "SmallBlindPosition": 1,
      "BigBlindPosition": 0,
      "Players": [
        {
          "Name": "Random",
          "Id": "nanlhrdqkzbzdgwizomihg",
          "Stack": 1240.0,
          "State": "Participating"
        },
        {
          "Name": "PokerShark",
          "Id": "lzetymnatpektjoxdrmpaq",
          "Stack": 760.0,
          "State": "Folded"
        }
      ],
      "RoundCount": 27,
      "Pocket": [
        "2C",
        "8D"
      ],
      "Pot": {
        "Amount": 30.0
      },
      "Winner": [
        {
          "Name": "Random",
          "Id": "nanlhrdqkzbzdgwizomihg",
          "Stack": 1240.0,
          "State": "Participating"
        }
      ],
      "History": [
        {
          "PlayerName": "PokerShark",
          "Stage": "Preflop",
          "Type": "Fold"
        }
      ],
      "OddsLog": []
    },
    {
      "SmallBlindPosition": 0,
      "BigBlindPosition": 1,
      "Players": [
        {
          "Name": "Random",
          "Id": "nanlhrdqkzbzdgwizomihg",
          "Stack": 1260.0,
          "State": "Participating"
        },
        {
          "Name": "PokerShark",
          "Id": "lzetymnatpektjoxdrmpaq",
          "Stack": 740.0,
          "State": "Folded"
        }
      ],
      "RoundCount": 28,
      "Pocket": [
        "3H",
        "JD"
      ],
      "Pot": {
        "Amount": 145.0
      },
      "Winner": [
        {
          "Name": "Random",
          "Id": "nanlhrdqkzbzdgwizomihg",
          "Stack": 1260.0,
          "State": "Participating"
        }
      ],
      "History": [
        {
          "PlayerName": "Random",
          "Amount": 125.0,
          "MinAmount": 125.0,
          "MaxAmount": 125.0,
          "Stage": "Preflop",
          "Type": "Raise"
        },
        {
          "PlayerName": "PokerShark",
          "Stage": "Preflop",
          "Type": "Fold"
        }
      ],
      "OddsLog": []
    },
    {
      "SmallBlindPosition": 1,
      "BigBlindPosition": 0,
      "Players": [
        {
          "Name": "Random",
          "Id": "nanlhrdqkzbzdgwizomihg",
          "Stack": 1270.0,
          "State": "Participating"
        },
        {
          "Name": "PokerShark",
          "Id": "lzetymnatpektjoxdrmpaq",
          "Stack": 730.0,
          "State": "Folded"
        }
      ],
      "RoundCount": 29,
      "Pocket": [
        "6D",
        "KD"
      ],
      "Pot": {
        "Amount": 30.0
      },
      "Winner": [
        {
          "Name": "Random",
          "Id": "nanlhrdqkzbzdgwizomihg",
          "Stack": 1270.0,
          "State": "Participating"
        }
      ],
      "History": [
        {
          "PlayerName": "PokerShark",
          "Stage": "Preflop",
          "Type": "Fold"
        }
      ],
      "OddsLog": []
    },
    {
      "SmallBlindPosition": 0,
      "BigBlindPosition": 1,
      "Players": [
        {
          "Name": "Random",
          "Id": "nanlhrdqkzbzdgwizomihg",
          "Stack": 1260.0,
          "State": "Folded"
        },
        {
          "Name": "PokerShark",
          "Id": "lzetymnatpektjoxdrmpaq",
          "Stack": 740.0,
          "State": "Participating"
        }
      ],
      "RoundCount": 30,
      "Pocket": [
        "7H",
        "3S"
      ],
      "Pot": {
        "Amount": 30.0
      },
      "Winner": [
        {
          "Name": "PokerShark",
          "Id": "lzetymnatpektjoxdrmpaq",
          "Stack": 740.0,
          "State": "Participating"
        }
      ],
      "History": [
        {
          "PlayerName": "Random",
          "Stage": "Preflop",
          "Type": "Fold"
        }
      ],
      "OddsLog": []
    },
    {
      "SmallBlindPosition": 1,
      "BigBlindPosition": 0,
      "Players": [
        {
          "Name": "Random",
          "Id": "nanlhrdqkzbzdgwizomihg",
          "Stack": 1270.0,
          "State": "Participating"
        },
        {
          "Name": "PokerShark",
          "Id": "lzetymnatpektjoxdrmpaq",
          "Stack": 730.0,
          "State": "Folded"
        }
      ],
      "RoundCount": 31,
      "Pocket": [
        "JD",
        "7D"
      ],
      "Pot": {
        "Amount": 30.0
      },
      "Winner": [
        {
          "Name": "Random",
          "Id": "nanlhrdqkzbzdgwizomihg",
          "Stack": 1270.0,
          "State": "Participating"
        }
      ],
      "History": [
        {
          "PlayerName": "PokerShark",
          "Stage": "Preflop",
          "Type": "Fold"
        }
      ],
      "OddsLog": []
    },
    {
      "SmallBlindPosition": 0,
      "BigBlindPosition": 1,
      "Players": [
        {
          "Name": "Random",
          "Id": "nanlhrdqkzbzdgwizomihg",
          "Stack": 1290.0,
          "State": "Participating"
        },
        {
          "Name": "PokerShark",
          "Id": "lzetymnatpektjoxdrmpaq",
          "Stack": 710.0,
          "State": "Folded"
        }
      ],
      "RoundCount": 32,
      "Pocket": [
        "4D",
        "4C"
      ],
      "Pot": {
        "Amount": 414.0
      },
      "Winner": [
        {
          "Name": "Random",
          "Id": "nanlhrdqkzbzdgwizomihg",
          "Stack": 1290.0,
          "State": "Participating"
        }
      ],
      "History": [
        {
          "PlayerName": "Random",
          "Amount": 394.0,
          "MinAmount": 394.0,
          "MaxAmount": 394.0,
          "Stage": "Preflop",
          "Type": "Raise"
        },
        {
          "PlayerName": "PokerShark",
          "Stage": "Preflop",
          "Type": "Fold"
        }
      ],
      "OddsLog": []
    },
    {
      "SmallBlindPosition": 1,
      "BigBlindPosition": 0,
      "Players": [
        {
          "Name": "Random",
          "Id": "nanlhrdqkzbzdgwizomihg",
          "Stack": 1300.0,
          "State": "Participating"
        },
        {
          "Name": "PokerShark",
          "Id": "lzetymnatpektjoxdrmpaq",
          "Stack": 700.0,
          "State": "Folded"
        }
      ],
      "RoundCount": 33,
      "Pocket": [
        "7C",
        "QH"
      ],
      "Pot": {
        "Amount": 30.0
      },
      "Winner": [
        {
          "Name": "Random",
          "Id": "nanlhrdqkzbzdgwizomihg",
          "Stack": 1300.0,
          "State": "Participating"
        }
      ],
      "History": [
        {
          "PlayerName": "PokerShark",
          "Stage": "Preflop",
          "Type": "Fold"
        }
      ],
      "OddsLog": []
    },
    {
      "SmallBlindPosition": 0,
      "BigBlindPosition": 1,
      "Players": [
        {
          "Name": "Random",
          "Id": "nanlhrdqkzbzdgwizomihg",
          "Stack": 1320.0,
          "State": "Participating"
        },
        {
          "Name": "PokerShark",
          "Id": "lzetymnatpektjoxdrmpaq",
          "Stack": 680.0,
          "State": "Folded"
        }
      ],
      "RoundCount": 34,
      "Pocket": [
        "3H",
        "7H"
      ],
      "Pot": {
        "Amount": 896.0
      },
      "Winner": [
        {
          "Name": "Random",
          "Id": "nanlhrdqkzbzdgwizomihg",
          "Stack": 1320.0,
          "State": "Participating"
        }
      ],
      "History": [
        {
          "PlayerName": "Random",
          "Amount": 876.0,
          "MinAmount": 876.0,
          "MaxAmount": 876.0,
          "Stage": "Preflop",
          "Type": "Raise"
        },
        {
          "PlayerName": "PokerShark",
          "Stage": "Preflop",
          "Type": "Fold"
        }
      ],
      "OddsLog": []
    },
    {
      "SmallBlindPosition": 1,
      "BigBlindPosition": 0,
      "Players": [
        {
          "Name": "Random",
          "Id": "nanlhrdqkzbzdgwizomihg",
          "Stack": 1330.0,
          "State": "Participating"
        },
        {
          "Name": "PokerShark",
          "Id": "lzetymnatpektjoxdrmpaq",
          "Stack": 670.0,
          "State": "Folded"
        }
      ],
      "RoundCount": 35,
      "Pocket": [
        "7C",
        "6D"
      ],
      "Pot": {
        "Amount": 30.0
      },
      "Winner": [
        {
          "Name": "Random",
          "Id": "nanlhrdqkzbzdgwizomihg",
          "Stack": 1330.0,
          "State": "Participating"
        }
      ],
      "History": [
        {
          "PlayerName": "PokerShark",
          "Stage": "Preflop",
          "Type": "Fold"
        }
      ],
      "OddsLog": []
    },
    {
      "SmallBlindPosition": 0,
      "BigBlindPosition": 1,
      "Players": [
        {
          "Name": "Random",
          "Id": "nanlhrdqkzbzdgwizomihg",
          "Stack": 1320.0,
          "State": "Folded"
        },
        {
          "Name": "PokerShark",
          "Id": "lzetymnatpektjoxdrmpaq",
          "Stack": 680.0,
          "State": "Participating"
        }
      ],
      "RoundCount": 36,
      "Pocket": [
        "2H",
        "AS"
      ],
      "Pot": {
        "Amount": 30.0
      },
      "Winner": [
        {
          "Name": "PokerShark",
          "Id": "lzetymnatpektjoxdrmpaq",
          "Stack": 680.0,
          "State": "Participating"
        }
      ],
      "History": [
        {
          "PlayerName": "Random",
          "Stage": "Preflop",
          "Type": "Fold"
        }
      ],
      "OddsLog": []
    },
    {
      "SmallBlindPosition": 1,
      "BigBlindPosition": 0,
      "Players": [
        {
          "Name": "Random",
          "Id": "nanlhrdqkzbzdgwizomihg",
          "Stack": 1330.0,
          "State": "Participating"
        },
        {
          "Name": "PokerShark",
          "Id": "lzetymnatpektjoxdrmpaq",
          "Stack": 670.0,
          "State": "Folded"
        }
      ],
      "RoundCount": 37,
      "Pocket": [
        "3S",
        "AH"
      ],
      "Pot": {
        "Amount": 30.0
      },
      "Winner": [
        {
          "Name": "Random",
          "Id": "nanlhrdqkzbzdgwizomihg",
          "Stack": 1330.0,
          "State": "Participating"
        }
      ],
      "History": [
        {
          "PlayerName": "PokerShark",
          "Stage": "Preflop",
          "Type": "Fold"
        }
      ],
      "OddsLog": []
    },
    {
      "SmallBlindPosition": 0,
      "BigBlindPosition": 1,
      "Players": [
        {
          "Name": "Random",
          "Id": "nanlhrdqkzbzdgwizomihg",
          "Stack": 1350.0,
          "State": "Participating"
        },
        {
          "Name": "PokerShark",
          "Id": "lzetymnatpektjoxdrmpaq",
          "Stack": 650.0,
          "State": "Folded"
        }
      ],
      "RoundCount": 38,
      "Pocket": [
        "JS",
        "4S"
      ],
      "Pot": {
        "Amount": 1244.0
      },
      "Winner": [
        {
          "Name": "Random",
          "Id": "nanlhrdqkzbzdgwizomihg",
          "Stack": 1350.0,
          "State": "Participating"
        }
      ],
      "History": [
        {
          "PlayerName": "Random",
          "Amount": 1224.0,
          "MinAmount": 1224.0,
          "MaxAmount": 1224.0,
          "Stage": "Preflop",
          "Type": "Raise"
        },
        {
          "PlayerName": "PokerShark",
          "Stage": "Preflop",
          "Type": "Fold"
        }
      ],
      "OddsLog": []
    },
    {
      "SmallBlindPosition": 1,
      "BigBlindPosition": 0,
      "Players": [
        {
          "Name": "Random",
          "Id": "nanlhrdqkzbzdgwizomihg",
          "Stack": 1360.0,
          "State": "Participating"
        },
        {
          "Name": "PokerShark",
          "Id": "lzetymnatpektjoxdrmpaq",
          "Stack": 640.0,
          "State": "Folded"
        }
      ],
      "RoundCount": 39,
      "Pocket": [
        "KC",
        "9S"
      ],
      "Pot": {
        "Amount": 30.0
      },
      "Winner": [
        {
          "Name": "Random",
          "Id": "nanlhrdqkzbzdgwizomihg",
          "Stack": 1360.0,
          "State": "Participating"
        }
      ],
      "History": [
        {
          "PlayerName": "PokerShark",
          "Stage": "Preflop",
          "Type": "Fold"
        }
      ],
      "OddsLog": []
    },
    {
      "SmallBlindPosition": 0,
      "BigBlindPosition": 1,
      "Players": [
        {
          "Name": "Random",
          "Id": "nanlhrdqkzbzdgwizomihg",
          "Stack": 1380.0,
          "State": "Participating"
        },
        {
          "Name": "PokerShark",
          "Id": "lzetymnatpektjoxdrmpaq",
          "Stack": 620.0,
          "State": "Folded"
        }
      ],
      "RoundCount": 40,
      "Pocket": [
        "2H",
        "2S"
      ],
      "Pot": {
        "Amount": 768.0
      },
      "Winner": [
        {
          "Name": "Random",
          "Id": "nanlhrdqkzbzdgwizomihg",
          "Stack": 1380.0,
          "State": "Participating"
        }
      ],
      "History": [
        {
          "PlayerName": "Random",
          "Amount": 748.0,
          "MinAmount": 748.0,
          "MaxAmount": 748.0,
          "Stage": "Preflop",
          "Type": "Raise"
        },
        {
          "PlayerName": "PokerShark",
          "Stage": "Preflop",
          "Type": "Fold"
        }
      ],
      "OddsLog": []
    },
    {
      "SmallBlindPosition": 1,
      "BigBlindPosition": 0,
      "Players": [
        {
          "Name": "Random",
          "Id": "nanlhrdqkzbzdgwizomihg",
          "Stack": 1390.0,
          "State": "Participating"
        },
        {
          "Name": "PokerShark",
          "Id": "lzetymnatpektjoxdrmpaq",
          "Stack": 610.0,
          "State": "Folded"
        }
      ],
      "RoundCount": 41,
      "Pocket": [
        "TD",
        "2C"
      ],
      "Pot": {
        "Amount": 30.0
      },
      "Winner": [
        {
          "Name": "Random",
          "Id": "nanlhrdqkzbzdgwizomihg",
          "Stack": 1390.0,
          "State": "Participating"
        }
      ],
      "History": [
        {
          "PlayerName": "PokerShark",
          "Stage": "Preflop",
          "Type": "Fold"
        }
      ],
      "OddsLog": []
    },
    {
      "SmallBlindPosition": 0,
      "BigBlindPosition": 1,
      "Players": [
        {
          "Name": "Random",
          "Id": "nanlhrdqkzbzdgwizomihg",
          "Stack": 1410.0,
          "State": "Participating"
        },
        {
          "Name": "PokerShark",
          "Id": "lzetymnatpektjoxdrmpaq",
          "Stack": 590.0,
          "State": "Folded"
        }
      ],
      "RoundCount": 42,
      "Pocket": [
        "8D",
        "7H"
      ],
      "Pot": {
        "Amount": 603.0
      },
      "Winner": [
        {
          "Name": "Random",
          "Id": "nanlhrdqkzbzdgwizomihg",
          "Stack": 1410.0,
          "State": "Participating"
        }
      ],
      "History": [
        {
          "PlayerName": "Random",
          "Amount": 583.0,
          "MinAmount": 583.0,
          "MaxAmount": 583.0,
          "Stage": "Preflop",
          "Type": "Raise"
        },
        {
          "PlayerName": "PokerShark",
          "Stage": "Preflop",
          "Type": "Fold"
        }
      ],
      "OddsLog": []
    },
    {
      "SmallBlindPosition": 1,
      "BigBlindPosition": 0,
      "Players": [
        {
          "Name": "Random",
          "Id": "nanlhrdqkzbzdgwizomihg",
          "Stack": 1420.0,
          "State": "Participating"
        },
        {
          "Name": "PokerShark",
          "Id": "lzetymnatpektjoxdrmpaq",
          "Stack": 580.0,
          "State": "Folded"
        }
      ],
      "RoundCount": 43,
      "Pocket": [
        "QH",
        "8S"
      ],
      "Pot": {
        "Amount": 30.0
      },
      "Winner": [
        {
          "Name": "Random",
          "Id": "nanlhrdqkzbzdgwizomihg",
          "Stack": 1420.0,
          "State": "Participating"
        }
      ],
      "History": [
        {
          "PlayerName": "PokerShark",
          "Stage": "Preflop",
          "Type": "Fold"
        }
      ],
      "OddsLog": []
    },
    {
      "SmallBlindPosition": 0,
      "BigBlindPosition": 1,
      "Players": [
        {
          "Name": "Random",
          "Id": "nanlhrdqkzbzdgwizomihg",
          "Stack": 1410.0,
          "State": "Folded"
        },
        {
          "Name": "PokerShark",
          "Id": "lzetymnatpektjoxdrmpaq",
          "Stack": 590.0,
          "State": "Participating"
        }
      ],
      "RoundCount": 44,
      "Pocket": [
        "4S",
        "AH"
      ],
      "Pot": {
        "Amount": 30.0
      },
      "Winner": [
        {
          "Name": "PokerShark",
          "Id": "lzetymnatpektjoxdrmpaq",
          "Stack": 590.0,
          "State": "Participating"
        }
      ],
      "History": [
        {
          "PlayerName": "Random",
          "Stage": "Preflop",
          "Type": "Fold"
        }
      ],
      "OddsLog": []
    },
    {
      "SmallBlindPosition": 1,
      "BigBlindPosition": 0,
      "Players": [
        {
          "Name": "Random",
          "Id": "nanlhrdqkzbzdgwizomihg",
          "Stack": 1420.0,
          "State": "Participating"
        },
        {
          "Name": "PokerShark",
          "Id": "lzetymnatpektjoxdrmpaq",
          "Stack": 580.0,
          "State": "Folded"
        }
      ],
      "RoundCount": 45,
      "Pocket": [
        "4C",
        "QC"
      ],
      "Pot": {
        "Amount": 30.0
      },
      "Winner": [
        {
          "Name": "Random",
          "Id": "nanlhrdqkzbzdgwizomihg",
          "Stack": 1420.0,
          "State": "Participating"
        }
      ],
      "History": [
        {
          "PlayerName": "PokerShark",
          "Stage": "Preflop",
          "Type": "Fold"
        }
      ],
      "OddsLog": []
    },
    {
      "SmallBlindPosition": 0,
      "BigBlindPosition": 1,
      "Players": [
        {
          "Name": "Random",
          "Id": "nanlhrdqkzbzdgwizomihg",
          "Stack": 1410.0,
          "State": "Folded"
        },
        {
          "Name": "PokerShark",
          "Id": "lzetymnatpektjoxdrmpaq",
          "Stack": 590.0,
          "State": "Participating"
        }
      ],
      "RoundCount": 46,
      "Pocket": [
        "7S",
        "4C"
      ],
      "Pot": {
        "Amount": 30.0
      },
      "Winner": [
        {
          "Name": "PokerShark",
          "Id": "lzetymnatpektjoxdrmpaq",
          "Stack": 590.0,
          "State": "Participating"
        }
      ],
      "History": [
        {
          "PlayerName": "Random",
          "Stage": "Preflop",
          "Type": "Fold"
        }
      ],
      "OddsLog": []
    },
    {
      "SmallBlindPosition": 1,
      "BigBlindPosition": 0,
      "Players": [
        {
          "Name": "Random",
          "Id": "nanlhrdqkzbzdgwizomihg",
          "Stack": 1420.0,
          "State": "Participating"
        },
        {
          "Name": "PokerShark",
          "Id": "lzetymnatpektjoxdrmpaq",
          "Stack": 580.0,
          "State": "Folded"
        }
      ],
      "RoundCount": 47,
      "Pocket": [
        "7C",
        "9H"
      ],
      "Pot": {
        "Amount": 30.0
      },
      "Winner": [
        {
          "Name": "Random",
          "Id": "nanlhrdqkzbzdgwizomihg",
          "Stack": 1420.0,
          "State": "Participating"
        }
      ],
      "History": [
        {
          "PlayerName": "PokerShark",
          "Stage": "Preflop",
          "Type": "Fold"
        }
      ],
      "OddsLog": []
    },
    {
      "SmallBlindPosition": 0,
      "BigBlindPosition": 1,
      "Players": [
        {
          "Name": "Random",
          "Id": "nanlhrdqkzbzdgwizomihg",
          "Stack": 1440.0,
          "State": "Participating"
        },
        {
          "Name": "PokerShark",
          "Id": "lzetymnatpektjoxdrmpaq",
          "Stack": 560.0,
          "State": "Folded"
        }
      ],
      "RoundCount": 48,
      "Pocket": [
        "6D",
        "7D"
      ],
      "Pot": {
        "Amount": 1424.0
      },
      "Winner": [
        {
          "Name": "Random",
          "Id": "nanlhrdqkzbzdgwizomihg",
          "Stack": 1440.0,
          "State": "Participating"
        }
      ],
      "History": [
        {
          "PlayerName": "Random",
          "Amount": 1404.0,
          "MinAmount": 1404.0,
          "MaxAmount": 1404.0,
          "Stage": "Preflop",
          "Type": "Raise"
        },
        {
          "PlayerName": "PokerShark",
          "Stage": "Preflop",
          "Type": "Fold"
        }
      ],
      "OddsLog": []
    },
    {
      "SmallBlindPosition": 1,
      "BigBlindPosition": 0,
      "Players": [
        {
          "Name": "Random",
          "Id": "nanlhrdqkzbzdgwizomihg",
          "Stack": 1450.0,
          "State": "Participating"
        },
        {
          "Name": "PokerShark",
          "Id": "lzetymnatpektjoxdrmpaq",
          "Stack": 550.0,
          "State": "Folded"
        }
      ],
      "RoundCount": 49,
      "Pocket": [
        "JD",
        "9C"
      ],
      "Pot": {
        "Amount": 30.0
      },
      "Winner": [
        {
          "Name": "Random",
          "Id": "nanlhrdqkzbzdgwizomihg",
          "Stack": 1450.0,
          "State": "Participating"
        }
      ],
      "History": [
        {
          "PlayerName": "PokerShark",
          "Stage": "Preflop",
          "Type": "Fold"
        }
      ],
      "OddsLog": []
    },
    {
      "SmallBlindPosition": 0,
      "BigBlindPosition": 1,
      "Players": [
        {
          "Name": "Random",
          "Id": "nanlhrdqkzbzdgwizomihg",
          "Stack": 1440.0,
          "State": "Folded"
        },
        {
          "Name": "PokerShark",
          "Id": "lzetymnatpektjoxdrmpaq",
          "Stack": 560.0,
          "State": "Participating"
        }
      ],
      "RoundCount": 50,
      "Pocket": [
        "3D",
        "9S"
      ],
      "Pot": {
        "Amount": 30.0
      },
      "Winner": [
        {
          "Name": "PokerShark",
          "Id": "lzetymnatpektjoxdrmpaq",
          "Stack": 560.0,
          "State": "Participating"
        }
      ],
      "History": [
        {
          "PlayerName": "Random",
          "Stage": "Preflop",
          "Type": "Fold"
        }
      ],
      "OddsLog": []
    },
    {
      "SmallBlindPosition": 1,
      "BigBlindPosition": 0,
      "Players": [
        {
          "Name": "Random",
          "Id": "nanlhrdqkzbzdgwizomihg",
          "Stack": 1450.0,
          "State": "Participating"
        },
        {
          "Name": "PokerShark",
          "Id": "lzetymnatpektjoxdrmpaq",
          "Stack": 550.0,
          "State": "Folded"
        }
      ],
      "RoundCount": 51,
      "Pocket": [
        "2D",
        "6H"
      ],
      "Pot": {
        "Amount": 30.0
      },
      "Winner": [
        {
          "Name": "Random",
          "Id": "nanlhrdqkzbzdgwizomihg",
          "Stack": 1450.0,
          "State": "Participating"
        }
      ],
      "History": [
        {
          "PlayerName": "PokerShark",
          "Stage": "Preflop",
          "Type": "Fold"
        }
      ],
      "OddsLog": []
    },
    {
      "SmallBlindPosition": 0,
      "BigBlindPosition": 1,
      "Players": [
        {
          "Name": "Random",
          "Id": "nanlhrdqkzbzdgwizomihg",
          "Stack": 1599.0,
          "State": "Participating"
        },
        {
          "Name": "PokerShark",
          "Id": "lzetymnatpektjoxdrmpaq",
          "Stack": 401.0,
          "State": "Folded"
        }
      ],
      "RoundCount": 52,
      "Board": [
        "TC",
        "7S",
        "8C"
      ],
      "Pocket": [
        "JH",
        "AD"
      ],
      "Pot": {
        "Amount": 899.0
      },
      "Winner": [
        {
          "Name": "Random",
          "Id": "nanlhrdqkzbzdgwizomihg",
          "Stack": 1599.0,
          "State": "Participating"
        }
      ],
      "History": [
        {
          "PlayerName": "Random",
          "Amount": 149.0,
          "MinAmount": 149.0,
          "MaxAmount": 149.0,
          "Stage": "Preflop",
          "Type": "Raise"
        },
        {
          "PlayerName": "PokerShark",
          "Amount": 149.0,
          "Stage": "Preflop",
          "Type": "Call"
        },
        {
          "PlayerName": "Random",
          "Amount": 601.0,
          "MinAmount": 601.0,
          "MaxAmount": 601.0,
          "Stage": "Flop",
          "Type": "Raise"
        },
        {
          "PlayerName": "PokerShark",
          "Stage": "Flop",
          "Type": "Fold"
        }
      ],
      "OddsLog": [
        "Flop, ehs: (0,5050850383220993, 0,542695130086736, 0,4513558741015791, 0,2995, 0,2738), pot: 899\r\ncall: 601, Cost: 1500.00, Probability: 0.51 , Cost: -730.00, Probability: 0.49, EV:-73162,26\r\nfold Cost: -129.00, Probability: 1.00\r\n"
      ]
    },
    {
      "SmallBlindPosition": 1,
      "BigBlindPosition": 0,
      "Players": [
        {
          "Name": "Random",
          "Id": "nanlhrdqkzbzdgwizomihg",
          "Stack": 1609.0,
          "State": "Participating"
        },
        {
          "Name": "PokerShark",
          "Id": "lzetymnatpektjoxdrmpaq",
          "Stack": 391.0,
          "State": "Folded"
        }
      ],
      "RoundCount": 53,
      "Pocket": [
        "AH",
        "2C"
      ],
      "Pot": {
        "Amount": 30.0
      },
      "Winner": [
        {
          "Name": "Random",
          "Id": "nanlhrdqkzbzdgwizomihg",
          "Stack": 1609.0,
          "State": "Participating"
        }
      ],
      "History": [
        {
          "PlayerName": "PokerShark",
          "Stage": "Preflop",
          "Type": "Fold"
        }
      ],
      "OddsLog": []
    },
    {
      "SmallBlindPosition": 0,
      "BigBlindPosition": 1,
      "Players": [
        {
          "Name": "Random",
          "Id": "nanlhrdqkzbzdgwizomihg",
          "Stack": 1629.0,
          "State": "Participating"
        },
        {
          "Name": "PokerShark",
          "Id": "lzetymnatpektjoxdrmpaq",
          "Stack": 371.0,
          "State": "Folded"
        }
      ],
      "RoundCount": 54,
      "Pocket": [
        "3D",
        "5S"
      ],
      "Pot": {
        "Amount": 423.0
      },
      "Winner": [
        {
          "Name": "Random",
          "Id": "nanlhrdqkzbzdgwizomihg",
          "Stack": 1629.0,
          "State": "Participating"
        }
      ],
      "History": [
        {
          "PlayerName": "Random",
          "Amount": 403.0,
          "MinAmount": 403.0,
          "MaxAmount": 403.0,
          "Stage": "Preflop",
          "Type": "Raise"
        },
        {
          "PlayerName": "PokerShark",
          "Stage": "Preflop",
          "Type": "Fold"
        }
      ],
      "OddsLog": []
    },
    {
      "SmallBlindPosition": 1,
      "BigBlindPosition": 0,
      "Players": [
        {
          "Name": "Random",
          "Id": "nanlhrdqkzbzdgwizomihg",
          "Stack": 1639.0,
          "State": "Participating"
        },
        {
          "Name": "PokerShark",
          "Id": "lzetymnatpektjoxdrmpaq",
          "Stack": 361.0,
          "State": "Folded"
        }
      ],
      "RoundCount": 55,
      "Pocket": [
        "7H",
        "QH"
      ],
      "Pot": {
        "Amount": 30.0
      },
      "Winner": [
        {
          "Name": "Random",
          "Id": "nanlhrdqkzbzdgwizomihg",
          "Stack": 1639.0,
          "State": "Participating"
        }
      ],
      "History": [
        {
          "PlayerName": "PokerShark",
          "Stage": "Preflop",
          "Type": "Fold"
        }
      ],
      "OddsLog": []
    },
    {
      "SmallBlindPosition": 0,
      "BigBlindPosition": 1,
      "Players": [
        {
          "Name": "Random",
          "Id": "nanlhrdqkzbzdgwizomihg",
          "Stack": 1659.0,
          "State": "Participating"
        },
        {
          "Name": "PokerShark",
          "Id": "lzetymnatpektjoxdrmpaq",
          "Stack": 341.0,
          "State": "Folded"
        }
      ],
      "RoundCount": 56,
      "Pocket": [
        "6D",
        "TH"
      ],
      "Pot": {
        "Amount": 577.0
      },
      "Winner": [
        {
          "Name": "Random",
          "Id": "nanlhrdqkzbzdgwizomihg",
          "Stack": 1659.0,
          "State": "Participating"
        }
      ],
      "History": [
        {
          "PlayerName": "Random",
          "Amount": 557.0,
          "MinAmount": 557.0,
          "MaxAmount": 557.0,
          "Stage": "Preflop",
          "Type": "Raise"
        },
        {
          "PlayerName": "PokerShark",
          "Stage": "Preflop",
          "Type": "Fold"
        }
      ],
      "OddsLog": []
    },
    {
      "SmallBlindPosition": 1,
      "BigBlindPosition": 0,
      "Players": [
        {
          "Name": "Random",
          "Id": "nanlhrdqkzbzdgwizomihg",
          "Stack": 1669.0,
          "State": "Participating"
        },
        {
          "Name": "PokerShark",
          "Id": "lzetymnatpektjoxdrmpaq",
          "Stack": 331.0,
          "State": "Folded"
        }
      ],
      "RoundCount": 57,
      "Pocket": [
        "7C",
        "6S"
      ],
      "Pot": {
        "Amount": 30.0
      },
      "Winner": [
        {
          "Name": "Random",
          "Id": "nanlhrdqkzbzdgwizomihg",
          "Stack": 1669.0,
          "State": "Participating"
        }
      ],
      "History": [
        {
          "PlayerName": "PokerShark",
          "Stage": "Preflop",
          "Type": "Fold"
        }
      ],
      "OddsLog": []
    },
    {
      "SmallBlindPosition": 0,
      "BigBlindPosition": 1,
      "Players": [
        {
          "Name": "Random",
          "Id": "nanlhrdqkzbzdgwizomihg",
          "Stack": 1689.0,
          "State": "Participating"
        },
        {
          "Name": "PokerShark",
          "Id": "lzetymnatpektjoxdrmpaq",
          "Stack": 311.0,
          "State": "Folded"
        }
      ],
      "RoundCount": 58,
      "Pocket": [
        "JS",
        "9S"
      ],
      "Pot": {
        "Amount": 783.0
      },
      "Winner": [
        {
          "Name": "Random",
          "Id": "nanlhrdqkzbzdgwizomihg",
          "Stack": 1689.0,
          "State": "Participating"
        }
      ],
      "History": [
        {
          "PlayerName": "Random",
          "Amount": 763.0,
          "MinAmount": 763.0,
          "MaxAmount": 763.0,
          "Stage": "Preflop",
          "Type": "Raise"
        },
        {
          "PlayerName": "PokerShark",
          "Stage": "Preflop",
          "Type": "Fold"
        }
      ],
      "OddsLog": []
    },
    {
      "SmallBlindPosition": 1,
      "BigBlindPosition": 0,
      "Players": [
        {
          "Name": "Random",
          "Id": "nanlhrdqkzbzdgwizomihg",
          "Stack": 1699.0,
          "State": "Participating"
        },
        {
          "Name": "PokerShark",
          "Id": "lzetymnatpektjoxdrmpaq",
          "Stack": 301.0,
          "State": "Folded"
        }
      ],
      "RoundCount": 59,
      "Pocket": [
        "9H",
        "7S"
      ],
      "Pot": {
        "Amount": 30.0
      },
      "Winner": [
        {
          "Name": "Random",
          "Id": "nanlhrdqkzbzdgwizomihg",
          "Stack": 1699.0,
          "State": "Participating"
        }
      ],
      "History": [
        {
          "PlayerName": "PokerShark",
          "Stage": "Preflop",
          "Type": "Fold"
        }
      ],
      "OddsLog": []
    },
    {
      "SmallBlindPosition": 0,
      "BigBlindPosition": 1,
      "Players": [
        {
          "Name": "Random",
          "Id": "nanlhrdqkzbzdgwizomihg",
          "Stack": 1689.0,
          "State": "Folded"
        },
        {
          "Name": "PokerShark",
          "Id": "lzetymnatpektjoxdrmpaq",
          "Stack": 311.0,
          "State": "Participating"
        }
      ],
      "RoundCount": 60,
      "Pocket": [
        "4S",
        "7C"
      ],
      "Pot": {
        "Amount": 30.0
      },
      "Winner": [
        {
          "Name": "PokerShark",
          "Id": "lzetymnatpektjoxdrmpaq",
          "Stack": 311.0,
          "State": "Participating"
        }
      ],
      "History": [
        {
          "PlayerName": "Random",
          "Stage": "Preflop",
          "Type": "Fold"
        }
      ],
      "OddsLog": []
    },
    {
      "SmallBlindPosition": 1,
      "BigBlindPosition": 0,
      "Players": [
        {
          "Name": "Random",
          "Id": "nanlhrdqkzbzdgwizomihg",
          "Stack": 1709.0,
          "State": "Participating"
        },
        {
          "Name": "PokerShark",
          "Id": "lzetymnatpektjoxdrmpaq",
          "Stack": 291.0,
          "State": "Folded"
        }
      ],
      "RoundCount": 61,
      "Pocket": [
        "TC",
        "KH"
      ],
      "Pot": {
        "Amount": 424.0
      },
      "Winner": [
        {
          "Name": "Random",
          "Id": "nanlhrdqkzbzdgwizomihg",
          "Stack": 1709.0,
          "State": "Participating"
        }
      ],
      "History": [
        {
          "PlayerName": "PokerShark",
          "Amount": 20.0,
          "Stage": "Preflop",
          "Type": "Call"
        },
        {
          "PlayerName": "Random",
          "Amount": 404.0,
          "MinAmount": 404.0,
          "MaxAmount": 404.0,
          "Stage": "Preflop",
          "Type": "Raise"
        },
        {
          "PlayerName": "PokerShark",
          "Stage": "Preflop",
          "Type": "Fold"
        }
      ],
      "OddsLog": []
    },
    {
      "SmallBlindPosition": 0,
      "BigBlindPosition": 1,
      "Players": [
        {
          "Name": "Random",
          "Id": "nanlhrdqkzbzdgwizomihg",
          "Stack": 1699.0,
          "State": "Folded"
        },
        {
          "Name": "PokerShark",
          "Id": "lzetymnatpektjoxdrmpaq",
          "Stack": 301.0,
          "State": "Participating"
        }
      ],
      "RoundCount": 62,
      "Pocket": [
        "4H",
        "6H"
      ],
      "Pot": {
        "Amount": 30.0
      },
      "Winner": [
        {
          "Name": "PokerShark",
          "Id": "lzetymnatpektjoxdrmpaq",
          "Stack": 301.0,
          "State": "Participating"
        }
      ],
      "History": [
        {
          "PlayerName": "Random",
          "Stage": "Preflop",
          "Type": "Fold"
        }
      ],
      "OddsLog": []
    },
    {
      "SmallBlindPosition": 1,
      "BigBlindPosition": 0,
      "Players": [
        {
          "Name": "Random",
          "Id": "nanlhrdqkzbzdgwizomihg",
          "Stack": 1709.0,
          "State": "Participating"
        },
        {
          "Name": "PokerShark",
          "Id": "lzetymnatpektjoxdrmpaq",
          "Stack": 291.0,
          "State": "Folded"
        }
      ],
      "RoundCount": 63,
      "Pocket": [
        "4S",
        "7C"
      ],
      "Pot": {
        "Amount": 30.0
      },
      "Winner": [
        {
          "Name": "Random",
          "Id": "nanlhrdqkzbzdgwizomihg",
          "Stack": 1709.0,
          "State": "Participating"
        }
      ],
      "History": [
        {
          "PlayerName": "PokerShark",
          "Stage": "Preflop",
          "Type": "Fold"
        }
      ],
      "OddsLog": []
    },
    {
      "SmallBlindPosition": 0,
      "BigBlindPosition": 1,
      "Players": [
        {
          "Name": "Random",
          "Id": "nanlhrdqkzbzdgwizomihg",
          "Stack": 1729.0,
          "State": "Participating"
        },
        {
          "Name": "PokerShark",
          "Id": "lzetymnatpektjoxdrmpaq",
          "Stack": 271.0,
          "State": "Folded"
        }
      ],
      "RoundCount": 64,
      "Pocket": [
        "4S",
        "9D"
      ],
      "Pot": {
        "Amount": 1165.0
      },
      "Winner": [
        {
          "Name": "Random",
          "Id": "nanlhrdqkzbzdgwizomihg",
          "Stack": 1729.0,
          "State": "Participating"
        }
      ],
      "History": [
        {
          "PlayerName": "Random",
          "Amount": 1145.0,
          "MinAmount": 1145.0,
          "MaxAmount": 1145.0,
          "Stage": "Preflop",
          "Type": "Raise"
        },
        {
          "PlayerName": "PokerShark",
          "Stage": "Preflop",
          "Type": "Fold"
        }
      ],
      "OddsLog": []
    },
    {
      "SmallBlindPosition": 1,
      "BigBlindPosition": 0,
      "Players": [
        {
          "Name": "Random",
          "Id": "nanlhrdqkzbzdgwizomihg",
          "Stack": 1739.0,
          "State": "Participating"
        },
        {
          "Name": "PokerShark",
          "Id": "lzetymnatpektjoxdrmpaq",
          "Stack": 261.0,
          "State": "Folded"
        }
      ],
      "RoundCount": 65,
      "Pocket": [
        "5S",
        "4C"
      ],
      "Pot": {
        "Amount": 30.0
      },
      "Winner": [
        {
          "Name": "Random",
          "Id": "nanlhrdqkzbzdgwizomihg",
          "Stack": 1739.0,
          "State": "Participating"
        }
      ],
      "History": [
        {
          "PlayerName": "PokerShark",
          "Stage": "Preflop",
          "Type": "Fold"
        }
      ],
      "OddsLog": []
    },
    {
      "SmallBlindPosition": 0,
      "BigBlindPosition": 1,
      "Players": [
        {
          "Name": "Random",
          "Id": "nanlhrdqkzbzdgwizomihg",
          "Stack": 1759.0,
          "State": "Participating"
        },
        {
          "Name": "PokerShark",
          "Id": "lzetymnatpektjoxdrmpaq",
          "Stack": 241.0,
          "State": "Folded"
        }
      ],
      "RoundCount": 66,
      "Pocket": [
        "3S",
        "4H"
      ],
      "Pot": {
        "Amount": 1051.0
      },
      "Winner": [
        {
          "Name": "Random",
          "Id": "nanlhrdqkzbzdgwizomihg",
          "Stack": 1759.0,
          "State": "Participating"
        }
      ],
      "History": [
        {
          "PlayerName": "Random",
          "Amount": 1031.0,
          "MinAmount": 1031.0,
          "MaxAmount": 1031.0,
          "Stage": "Preflop",
          "Type": "Raise"
        },
        {
          "PlayerName": "PokerShark",
          "Stage": "Preflop",
          "Type": "Fold"
        }
      ],
      "OddsLog": []
    },
    {
      "SmallBlindPosition": 1,
      "BigBlindPosition": 0,
      "Players": [
        {
          "Name": "Random",
          "Id": "nanlhrdqkzbzdgwizomihg",
          "Stack": 1769.0,
          "State": "Participating"
        },
        {
          "Name": "PokerShark",
          "Id": "lzetymnatpektjoxdrmpaq",
          "Stack": 231.0,
          "State": "Folded"
        }
      ],
      "RoundCount": 67,
      "Pocket": [
        "3H",
        "TC"
      ],
      "Pot": {
        "Amount": 30.0
      },
      "Winner": [
        {
          "Name": "Random",
          "Id": "nanlhrdqkzbzdgwizomihg",
          "Stack": 1769.0,
          "State": "Participating"
        }
      ],
      "History": [
        {
          "PlayerName": "PokerShark",
          "Stage": "Preflop",
          "Type": "Fold"
        }
      ],
      "OddsLog": []
    },
    {
      "SmallBlindPosition": 0,
      "BigBlindPosition": 1,
      "Players": [
        {
          "Name": "Random",
          "Id": "nanlhrdqkzbzdgwizomihg",
          "Stack": 1789.0,
          "State": "Participating"
        },
        {
          "Name": "PokerShark",
          "Id": "lzetymnatpektjoxdrmpaq",
          "Stack": 211.0,
          "State": "Folded"
        }
      ],
      "RoundCount": 68,
      "Pocket": [
        "4H",
        "6C"
      ],
      "Pot": {
        "Amount": 744.0
      },
      "Winner": [
        {
          "Name": "Random",
          "Id": "nanlhrdqkzbzdgwizomihg",
          "Stack": 1789.0,
          "State": "Participating"
        }
      ],
      "History": [
        {
          "PlayerName": "Random",
          "Amount": 724.0,
          "MinAmount": 724.0,
          "MaxAmount": 724.0,
          "Stage": "Preflop",
          "Type": "Raise"
        },
        {
          "PlayerName": "PokerShark",
          "Stage": "Preflop",
          "Type": "Fold"
        }
      ],
      "OddsLog": []
    },
    {
      "SmallBlindPosition": 1,
      "BigBlindPosition": 0,
      "Players": [
        {
          "Name": "Random",
          "Id": "nanlhrdqkzbzdgwizomihg",
          "Stack": 1799.0,
          "State": "Participating"
        },
        {
          "Name": "PokerShark",
          "Id": "lzetymnatpektjoxdrmpaq",
          "Stack": 201.0,
          "State": "Folded"
        }
      ],
      "RoundCount": 69,
      "Pocket": [
        "6H",
        "AS"
      ],
      "Pot": {
        "Amount": 30.0
      },
      "Winner": [
        {
          "Name": "Random",
          "Id": "nanlhrdqkzbzdgwizomihg",
          "Stack": 1799.0,
          "State": "Participating"
        }
      ],
      "History": [
        {
          "PlayerName": "PokerShark",
          "Stage": "Preflop",
          "Type": "Fold"
        }
      ],
      "OddsLog": []
    },
    {
      "SmallBlindPosition": 0,
      "BigBlindPosition": 1,
      "Players": [
        {
          "Name": "Random",
          "Id": "nanlhrdqkzbzdgwizomihg",
          "Stack": 1819.0,
          "State": "Participating"
        },
        {
          "Name": "PokerShark",
          "Id": "lzetymnatpektjoxdrmpaq",
          "Stack": 181.0,
          "State": "Folded"
        }
      ],
      "RoundCount": 70,
      "Pocket": [
        "TS",
        "4D"
      ],
      "Pot": {
        "Amount": 1198.0
      },
      "Winner": [
        {
          "Name": "Random",
          "Id": "nanlhrdqkzbzdgwizomihg",
          "Stack": 1819.0,
          "State": "Participating"
        }
      ],
      "History": [
        {
          "PlayerName": "Random",
          "Amount": 1178.0,
          "MinAmount": 1178.0,
          "MaxAmount": 1178.0,
          "Stage": "Preflop",
          "Type": "Raise"
        },
        {
          "PlayerName": "PokerShark",
          "Stage": "Preflop",
          "Type": "Fold"
        }
      ],
      "OddsLog": []
    },
    {
      "SmallBlindPosition": 1,
      "BigBlindPosition": 0,
      "Players": [
        {
          "Name": "Random",
          "Id": "nanlhrdqkzbzdgwizomihg",
          "Stack": 1829.0,
          "State": "Participating"
        },
        {
          "Name": "PokerShark",
          "Id": "lzetymnatpektjoxdrmpaq",
          "Stack": 171.0,
          "State": "Folded"
        }
      ],
      "RoundCount": 71,
      "Pocket": [
        "9D",
        "JC"
      ],
      "Pot": {
        "Amount": 30.0
      },
      "Winner": [
        {
          "Name": "Random",
          "Id": "nanlhrdqkzbzdgwizomihg",
          "Stack": 1829.0,
          "State": "Participating"
        }
      ],
      "History": [
        {
          "PlayerName": "PokerShark",
          "Stage": "Preflop",
          "Type": "Fold"
        }
      ],
      "OddsLog": []
    },
    {
      "SmallBlindPosition": 0,
      "BigBlindPosition": 1,
      "Players": [
        {
          "Name": "Random",
          "Id": "nanlhrdqkzbzdgwizomihg",
          "Stack": 1849.0,
          "State": "Participating"
        },
        {
          "Name": "PokerShark",
          "Id": "lzetymnatpektjoxdrmpaq",
          "Stack": 151.0,
          "State": "Folded"
        }
      ],
      "RoundCount": 72,
      "Pocket": [
        "7C",
        "5C"
      ],
      "Pot": {
        "Amount": 264.0
      },
      "Winner": [
        {
          "Name": "Random",
          "Id": "nanlhrdqkzbzdgwizomihg",
          "Stack": 1849.0,
          "State": "Participating"
        }
      ],
      "History": [
        {
          "PlayerName": "Random",
          "Amount": 244.0,
          "MinAmount": 244.0,
          "MaxAmount": 244.0,
          "Stage": "Preflop",
          "Type": "Raise"
        },
        {
          "PlayerName": "PokerShark",
          "Stage": "Preflop",
          "Type": "Fold"
        }
      ],
      "OddsLog": []
    },
    {
      "SmallBlindPosition": 1,
      "BigBlindPosition": 0,
      "Players": [
        {
          "Name": "Random",
          "Id": "nanlhrdqkzbzdgwizomihg",
          "Stack": 1859.0,
          "State": "Participating"
        },
        {
          "Name": "PokerShark",
          "Id": "lzetymnatpektjoxdrmpaq",
          "Stack": 141.0,
          "State": "Folded"
        }
      ],
      "RoundCount": 73,
      "Pocket": [
        "5S",
        "8C"
      ],
      "Pot": {
        "Amount": 30.0
      },
      "Winner": [
        {
          "Name": "Random",
          "Id": "nanlhrdqkzbzdgwizomihg",
          "Stack": 1859.0,
          "State": "Participating"
        }
      ],
      "History": [
        {
          "PlayerName": "PokerShark",
          "Stage": "Preflop",
          "Type": "Fold"
        }
      ],
      "OddsLog": []
    },
    {
      "SmallBlindPosition": 0,
      "BigBlindPosition": 1,
      "Players": [
        {
          "Name": "Random",
          "Id": "nanlhrdqkzbzdgwizomihg",
          "Stack": 1849.0,
          "State": "Folded"
        },
        {
          "Name": "PokerShark",
          "Id": "lzetymnatpektjoxdrmpaq",
          "Stack": 151.0,
          "State": "Participating"
        }
      ],
      "RoundCount": 74,
      "Pocket": [
        "AD",
        "7C"
      ],
      "Pot": {
        "Amount": 30.0
      },
      "Winner": [
        {
          "Name": "PokerShark",
          "Id": "lzetymnatpektjoxdrmpaq",
          "Stack": 151.0,
          "State": "Participating"
        }
      ],
      "History": [
        {
          "PlayerName": "Random",
          "Stage": "Preflop",
          "Type": "Fold"
        }
      ],
      "OddsLog": []
    },
    {
      "SmallBlindPosition": 1,
      "BigBlindPosition": 0,
      "Players": [
        {
          "Name": "Random",
          "Id": "nanlhrdqkzbzdgwizomihg",
          "Stack": 1859.0,
          "State": "Participating"
        },
        {
          "Name": "PokerShark",
          "Id": "lzetymnatpektjoxdrmpaq",
          "Stack": 141.0,
          "State": "Folded"
        }
      ],
      "RoundCount": 75,
      "Pocket": [
        "9H",
        "4C"
      ],
      "Pot": {
        "Amount": 30.0
      },
      "Winner": [
        {
          "Name": "Random",
          "Id": "nanlhrdqkzbzdgwizomihg",
          "Stack": 1859.0,
          "State": "Participating"
        }
      ],
      "History": [
        {
          "PlayerName": "PokerShark",
          "Stage": "Preflop",
          "Type": "Fold"
        }
      ],
      "OddsLog": []
    },
    {
      "SmallBlindPosition": 0,
      "BigBlindPosition": 1,
      "Players": [
        {
          "Name": "Random",
          "Id": "nanlhrdqkzbzdgwizomihg",
          "Stack": 1849.0,
          "State": "Folded"
        },
        {
          "Name": "PokerShark",
          "Id": "lzetymnatpektjoxdrmpaq",
          "Stack": 151.0,
          "State": "Participating"
        }
      ],
      "RoundCount": 76,
      "Pocket": [
        "AC",
        "QH"
      ],
      "Pot": {
        "Amount": 30.0
      },
      "Winner": [
        {
          "Name": "PokerShark",
          "Id": "lzetymnatpektjoxdrmpaq",
          "Stack": 151.0,
          "State": "Participating"
        }
      ],
      "History": [
        {
          "PlayerName": "Random",
          "Stage": "Preflop",
          "Type": "Fold"
        }
      ],
      "OddsLog": []
    },
    {
      "SmallBlindPosition": 1,
      "BigBlindPosition": 0,
      "Players": [
        {
          "Name": "Random",
          "Id": "nanlhrdqkzbzdgwizomihg",
          "Stack": 1859.0,
          "State": "Participating"
        },
        {
          "Name": "PokerShark",
          "Id": "lzetymnatpektjoxdrmpaq",
          "Stack": 141.0,
          "State": "Folded"
        }
      ],
      "RoundCount": 77,
      "Pocket": [
        "4H",
        "7S"
      ],
      "Pot": {
        "Amount": 30.0
      },
      "Winner": [
        {
          "Name": "Random",
          "Id": "nanlhrdqkzbzdgwizomihg",
          "Stack": 1859.0,
          "State": "Participating"
        }
      ],
      "History": [
        {
          "PlayerName": "PokerShark",
          "Stage": "Preflop",
          "Type": "Fold"
        }
      ],
      "OddsLog": []
    },
    {
      "SmallBlindPosition": 0,
      "BigBlindPosition": 1,
      "Players": [
        {
          "Name": "Random",
          "Id": "nanlhrdqkzbzdgwizomihg",
          "Stack": 1879.0,
          "State": "Participating"
        },
        {
          "Name": "PokerShark",
          "Id": "lzetymnatpektjoxdrmpaq",
          "Stack": 121.0,
          "State": "Folded"
        }
      ],
      "RoundCount": 78,
      "Pocket": [
        "AD",
        "6S"
      ],
      "Pot": {
        "Amount": 1682.0
      },
      "Winner": [
        {
          "Name": "Random",
          "Id": "nanlhrdqkzbzdgwizomihg",
          "Stack": 1879.0,
          "State": "Participating"
        }
      ],
      "History": [
        {
          "PlayerName": "Random",
          "Amount": 1662.0,
          "MinAmount": 1662.0,
          "MaxAmount": 1662.0,
          "Stage": "Preflop",
          "Type": "Raise"
        },
        {
          "PlayerName": "PokerShark",
          "Stage": "Preflop",
          "Type": "Fold"
        }
      ],
      "OddsLog": []
    },
    {
      "SmallBlindPosition": 1,
      "BigBlindPosition": 0,
      "Players": [
        {
          "Name": "Random",
          "Id": "nanlhrdqkzbzdgwizomihg",
          "Stack": 1889.0,
          "State": "Participating"
        },
        {
          "Name": "PokerShark",
          "Id": "lzetymnatpektjoxdrmpaq",
          "Stack": 111.0,
          "State": "Folded"
        }
      ],
      "RoundCount": 79,
      "Pocket": [
        "QD",
        "6C"
      ],
      "Pot": {
        "Amount": 30.0
      },
      "Winner": [
        {
          "Name": "Random",
          "Id": "nanlhrdqkzbzdgwizomihg",
          "Stack": 1889.0,
          "State": "Participating"
        }
      ],
      "History": [
        {
          "PlayerName": "PokerShark",
          "Stage": "Preflop",
          "Type": "Fold"
        }
      ],
      "OddsLog": []
    },
    {
      "SmallBlindPosition": 0,
      "BigBlindPosition": 1,
      "Players": [
        {
          "Name": "Random",
          "Id": "nanlhrdqkzbzdgwizomihg",
          "Stack": 1879.0,
          "State": "Folded"
        },
        {
          "Name": "PokerShark",
          "Id": "lzetymnatpektjoxdrmpaq",
          "Stack": 121.0,
          "State": "Participating"
        }
      ],
      "RoundCount": 80,
      "Pocket": [
        "JC",
        "9C"
      ],
      "Pot": {
        "Amount": 30.0
      },
      "Winner": [
        {
          "Name": "PokerShark",
          "Id": "lzetymnatpektjoxdrmpaq",
          "Stack": 121.0,
          "State": "Participating"
        }
      ],
      "History": [
        {
          "PlayerName": "Random",
          "Stage": "Preflop",
          "Type": "Fold"
        }
      ],
      "OddsLog": []
    },
    {
      "SmallBlindPosition": 1,
      "BigBlindPosition": 0,
      "Players": [
        {
          "Name": "Random",
          "Id": "nanlhrdqkzbzdgwizomihg",
          "Stack": 1889.0,
          "State": "Participating"
        },
        {
          "Name": "PokerShark",
          "Id": "lzetymnatpektjoxdrmpaq",
          "Stack": 111.0,
          "State": "Folded"
        }
      ],
      "RoundCount": 81,
      "Pocket": [
        "9D",
        "6S"
      ],
      "Pot": {
        "Amount": 30.0
      },
      "Winner": [
        {
          "Name": "Random",
          "Id": "nanlhrdqkzbzdgwizomihg",
          "Stack": 1889.0,
          "State": "Participating"
        }
      ],
      "History": [
        {
          "PlayerName": "PokerShark",
          "Stage": "Preflop",
          "Type": "Fold"
        }
      ],
      "OddsLog": []
    },
    {
      "SmallBlindPosition": 0,
      "BigBlindPosition": 1,
      "Players": [
        {
          "Name": "Random",
          "Id": "nanlhrdqkzbzdgwizomihg",
          "Stack": 1909.0,
          "State": "Participating"
        },
        {
          "Name": "PokerShark",
          "Id": "lzetymnatpektjoxdrmpaq",
          "Stack": 91.0,
          "State": "Folded"
        }
      ],
      "RoundCount": 82,
      "Pocket": [
        "9D",
        "6C"
      ],
      "Pot": {
        "Amount": 1496.0
      },
      "Winner": [
        {
          "Name": "Random",
          "Id": "nanlhrdqkzbzdgwizomihg",
          "Stack": 1909.0,
          "State": "Participating"
        }
      ],
      "History": [
        {
          "PlayerName": "Random",
          "Amount": 1476.0,
          "MinAmount": 1476.0,
          "MaxAmount": 1476.0,
          "Stage": "Preflop",
          "Type": "Raise"
        },
        {
          "PlayerName": "PokerShark",
          "Stage": "Preflop",
          "Type": "Fold"
        }
      ],
      "OddsLog": []
    },
    {
      "SmallBlindPosition": 1,
      "BigBlindPosition": 0,
      "Players": [
        {
          "Name": "Random",
          "Id": "nanlhrdqkzbzdgwizomihg",
          "Stack": 1929.0,
          "State": "Participating"
        },
        {
          "Name": "PokerShark",
          "Id": "lzetymnatpektjoxdrmpaq",
          "Stack": 71.0,
          "State": "Folded"
        }
      ],
      "RoundCount": 83,
      "Pocket": [
        "8D",
        "8S"
      ],
      "Pot": {
        "Amount": 811.0
      },
      "Winner": [
        {
          "Name": "Random",
          "Id": "nanlhrdqkzbzdgwizomihg",
          "Stack": 1929.0,
          "State": "Participating"
        }
      ],
      "History": [
        {
          "PlayerName": "PokerShark",
          "Amount": 20.0,
          "Stage": "Preflop",
          "Type": "Call"
        },
        {
          "PlayerName": "Random",
          "Amount": 791.0,
          "MinAmount": 791.0,
          "MaxAmount": 791.0,
          "Stage": "Preflop",
          "Type": "Raise"
        },
        {
          "PlayerName": "PokerShark",
          "Stage": "Preflop",
          "Type": "Fold"
        }
      ],
      "OddsLog": []
    },
    {
      "SmallBlindPosition": 0,
      "BigBlindPosition": 1,
      "Players": [
        {
          "Name": "Random",
          "Id": "nanlhrdqkzbzdgwizomihg",
          "Stack": 1949.0,
          "State": "Participating"
        },
        {
          "Name": "PokerShark",
          "Id": "lzetymnatpektjoxdrmpaq",
          "Stack": 51.0,
          "State": "Folded"
        }
      ],
      "RoundCount": 84,
      "Pocket": [
        "QH",
        "TC"
      ],
      "Pot": {
        "Amount": 327.0
      },
      "Winner": [
        {
          "Name": "Random",
          "Id": "nanlhrdqkzbzdgwizomihg",
          "Stack": 1949.0,
          "State": "Participating"
        }
      ],
      "History": [
        {
          "PlayerName": "Random",
          "Amount": 307.0,
          "MinAmount": 307.0,
          "MaxAmount": 307.0,
          "Stage": "Preflop",
          "Type": "Raise"
        },
        {
          "PlayerName": "PokerShark",
          "Stage": "Preflop",
          "Type": "Fold"
        }
      ],
      "OddsLog": []
    },
    {
      "SmallBlindPosition": 1,
      "BigBlindPosition": 0,
      "Players": [
        {
          "Name": "Random",
          "Id": "nanlhrdqkzbzdgwizomihg",
          "Stack": 1959.0,
          "State": "Participating"
        },
        {
          "Name": "PokerShark",
          "Id": "lzetymnatpektjoxdrmpaq",
          "Stack": 41.0,
          "State": "Folded"
        }
      ],
      "RoundCount": 85,
      "Pocket": [
        "7S",
        "5C"
      ],
      "Pot": {
        "Amount": 30.0
      },
      "Winner": [
        {
          "Name": "Random",
          "Id": "nanlhrdqkzbzdgwizomihg",
          "Stack": 1959.0,
          "State": "Participating"
        }
      ],
      "History": [
        {
          "PlayerName": "PokerShark",
          "Stage": "Preflop",
          "Type": "Fold"
        }
      ],
      "OddsLog": []
    },
    {
      "SmallBlindPosition": 0,
      "BigBlindPosition": 1,
      "Players": [
        {
          "Name": "Random",
          "Id": "nanlhrdqkzbzdgwizomihg",
          "Stack": 1979.0,
          "State": "Participating"
        },
        {
          "Name": "PokerShark",
          "Id": "lzetymnatpektjoxdrmpaq",
          "Stack": 21.0,
          "State": "Folded"
        }
      ],
      "RoundCount": 86,
      "Pocket": [
        "JS",
        "4H"
      ],
      "Pot": {
        "Amount": 1957.0
      },
      "Winner": [
        {
          "Name": "Random",
          "Id": "nanlhrdqkzbzdgwizomihg",
          "Stack": 1979.0,
          "State": "Participating"
        }
      ],
      "History": [
        {
          "PlayerName": "Random",
          "Amount": 1937.0,
          "MinAmount": 1937.0,
          "MaxAmount": 1937.0,
          "Stage": "Preflop",
          "Type": "Raise"
        },
        {
          "PlayerName": "PokerShark",
          "Stage": "Preflop",
          "Type": "Fold"
        }
      ],
      "OddsLog": []
    },
    {
      "SmallBlindPosition": 1,
      "BigBlindPosition": 0,
      "Players": [
        {
          "Name": "Random",
          "Id": "nanlhrdqkzbzdgwizomihg",
          "Stack": 1989.0,
          "State": "Participating"
        },
        {
          "Name": "PokerShark",
          "Id": "lzetymnatpektjoxdrmpaq",
          "Stack": 11.0,
          "State": "Folded"
        }
      ],
      "RoundCount": 87,
      "Pocket": [
        "4D",
        "KC"
      ],
      "Pot": {
        "Amount": 30.0
      },
      "Winner": [
        {
          "Name": "Random",
          "Id": "nanlhrdqkzbzdgwizomihg",
          "Stack": 1989.0,
          "State": "Participating"
        }
      ],
      "History": [
        {
          "PlayerName": "PokerShark",
          "Stage": "Preflop",
          "Type": "Fold"
        }
      ],
      "OddsLog": []
    }
  ],
  "PlayerModels": [
    {
      "Player": {
        "Name": "Random",
        "Id": "nanlhrdqkzbzdgwizomihg"
      },
      "VPIP": 67.3469387755102,
      "PFR": 67.3469387755102,
      "PFF": 32.6530612244898,
      "WTSD": 68.0,
      "PSDF": 0.0,
      "WSD": 0.0,
      "WWSF": 100.0,
      "Win": 0,
      "Lost": 0,
      "PostFlopWin": 1,
      "PostFlopLost": 0,
      "PlayingStyle": "TightAggressive",
      "WeightTable": "1,1,1,1,1,1,1,1,1,1,1,1,1\r\n1,1,1,1,1,0.7999999999999999,0.7999999999999999,0.7999999999999999,0.7999999999999999,0.7999999999999999,0.7999999999999999,0.7999999999999999,0.7999999999999999\r\n1,1,1,1,1,1,0.7999999999999999,0.7999999999999999,0.7999999999999999,0.7999999999999999,0.7999999999999999,0.7999999999999999,0.7999999999999999\r\n1,1,1,1,1,1,0.7999999999999999,0.7999999999999999,0.7999999999999999,0.7999999999999999,0.7999999999999999,0.7999999999999999,0.7999999999999999\r\n0.7999999999999999,0.7999999999999999,0.7999999999999999,1,1,1,1,0.7999999999999999,0.7999999999999999,0.7999999999999999,0.7999999999999999,0.7999999999999999,0.7999999999999999\r\n0.7999999999999999,0.7999999999999999,0.7999999999999999,0.7999999999999999,0.7999999999999999,1,1,1,0.7999999999999999,0.7999999999999999,0.7999999999999999,0.7999999999999999,0.7999999999999999\r\n0.7999999999999999,0.7999999999999999,0.7999999999999999,0.7999999999999999,0.7999999999999999,0.7999999999999999,1,1,0.7999999999999999,0.7999999999999999,0.7999999999999999,0.7999999999999999,0.7999999999999999\r\n0.7999999999999999,0.7999999999999999,0.7999999999999999,0.7999999999999999,0.7999999999999999,0.7999999999999999,0.7999999999999999,1,1,0.7999999999999999,0.7999999999999999,0.7999999999999999,0.7999999999999999\r\n0.7999999999999999,0.7999999999999999,0.7999999999999999,0.7999999999999999,0.7999999999999999,0.7999999999999999,0.7999999999999999,0.7999999999999999,0.7999999999999999,1,0.7999999999999999,0.7999999999999999,0.7999999999999999\r\n0.7999999999999999,0.7999999999999999,0.7999999999999999,0.7999999999999999,0.7999999999999999,0.7999999999999999,0.7999999999999999,0.7999999999999999,0.7999999999999999,0.7999999999999999,0.7999999999999999,0.7999999999999999,0.7999999999999999\r\n0.7999999999999999,0.7999999999999999,0.7999999999999999,0.7999999999999999,0.7999999999999999,0.7999999999999999,0.7999999999999999,0.7999999999999999,0.7999999999999999,0.7999999999999999,0.7999999999999999,0.7999999999999999,0.7999999999999999\r\n0.7999999999999999,0.7999999999999999,0.7999999999999999,0.7999999999999999,0.7999999999999999,0.7999999999999999,0.7999999999999999,0.7999999999999999,0.7999999999999999,0.7999999999999999,0.7999999999999999,0.7999999999999999,0.7999999999999999\r\n0.7999999999999999,0.7999999999999999,0.7999999999999999,0.7999999999999999,0.7999999999999999,0.7999999999999999,0.7999999999999999,0.7999999999999999,0.7999999999999999,0.7999999999999999,0.7999999999999999,0.7999999999999999,0.7999999999999999\r\n"
    },
    {
      "Player": {
        "Name": "PokerShark",
        "Id": "lzetymnatpektjoxdrmpaq"
      },
      "VPIP": 9.090909090909092,
      "PFR": 1.2987012987012987,
      "PFF": 90.9090909090909,
      "WTSD": 8.974358974358978,
      "PSDF": 100.0,
      "WSD": 0.0,
      "WWSF": 0.0,
      "Win": 0,
      "Lost": 1,
      "PostFlopWin": 0,
      "PostFlopLost": 1,
      "PlayingStyle": "TightPassive",
      "WeightTable": "1,1,1,1,1,0.8666666666666667,0.8666666666666667,0.8666666666666667,0.8666666666666667,0.8666666666666667,0.8666666666666667,0.8666666666666667,0.8666666666666667\r\n1,1,1,1,0.9333333333333332,0.6333333333333333,0.5333333333333333,0.5333333333333333,0.5333333333333333,0.5333333333333333,0.5333333333333333,0.5333333333333333,0.5333333333333333\r\n1,0.9333333333333332,1,1,0.9333333333333332,0.8666666666666667,0.5333333333333333,0.4666666666666666,0.4666666666666666,0.4666666666666666,0.4666666666666666,0.4666666666666666,0.4666666666666666\r\n0.9333333333333332,0.8666666666666667,0.8666666666666667,1,1,0.9333333333333332,0.6333333333333333,0.4666666666666666,0.4666666666666666,0.4666666666666666,0.4666666666666666,0.4666666666666666,0.4666666666666666\r\n0.6333333333333333,0.6333333333333333,0.6333333333333333,0.8666666666666667,1,0.9333333333333332,0.8666666666666667,0.5333333333333333,0.4666666666666666,0.4666666666666666,0.4666666666666666,0.4666666666666666,0.4666666666666666\r\n0.4666666666666666,0.4666666666666666,0.4666666666666666,0.5333333333333333,0.5333333333333333,1,0.9333333333333332,0.8666666666666667,0.4666666666666666,0.4666666666666666,0.4666666666666666,0.4666666666666666,0.4666666666666666\r\n0.4666666666666666,0.4666666666666666,0.4666666666666666,0.4666666666666666,0.4666666666666666,0.5333333333333333,0.9333333333333332,0.8666666666666667,0.6333333333333333,0.4666666666666666,0.4666666666666666,0.4666666666666666,0.4666666666666666\r\n0.4666666666666666,0.4666666666666666,0.4666666666666666,0.4666666666666666,0.4666666666666666,0.4666666666666666,0.4666666666666666,0.8666666666666667,0.8666666666666667,0.6333333333333333,0.4666666666666666,0.4666666666666666,0.4666666666666666\r\n0.4666666666666666,0.4666666666666666,0.4666666666666666,0.4666666666666666,0.4666666666666666,0.4666666666666666,0.4666666666666666,0.4666666666666666,0.6333333333333333,0.8666666666666667,0.5333333333333333,0.4666666666666666,0.4666666666666666\r\n0.4666666666666666,0.4666666666666666,0.4666666666666666,0.4666666666666666,0.4666666666666666,0.4666666666666666,0.4666666666666666,0.4666666666666666,0.4666666666666666,0.6333333333333333,0.6333333333333333,0.5333333333333333,0.4666666666666666\r\n0.4666666666666666,0.4666666666666666,0.4666666666666666,0.4666666666666666,0.4666666666666666,0.4666666666666666,0.4666666666666666,0.4666666666666666,0.4666666666666666,0.4666666666666666,0.5333333333333333,0.5333333333333333,0.4666666666666666\r\n0.4666666666666666,0.4666666666666666,0.4666666666666666,0.4666666666666666,0.4666666666666666,0.4666666666666666,0.4666666666666666,0.4666666666666666,0.4666666666666666,0.4666666666666666,0.4666666666666666,0.5333333333333333,0.4666666666666666\r\n0.4666666666666666,0.4666666666666666,0.4666666666666666,0.4666666666666666,0.4666666666666666,0.4666666666666666,0.4666666666666666,0.4666666666666666,0.4666666666666666,0.4666666666666666,0.4666666666666666,0.4666666666666666,0.5333333333333333\r\n"
    }
  ],
  "Results": [
    {
      "Player": {
        "Name": "Random",
        "Id": "nanlhrdqkzbzdgwizomihg"
      },
      "won": 71,
      "drew": 0,
      "lost": 16,
      "InitialStack": 1000.0,
      "Stack": 1989.0
    },
    {
      "Player": {
        "Name": "PokerShark",
        "Id": "lzetymnatpektjoxdrmpaq"
      },
      "won": 16,
      "drew": 0,
      "lost": 71,
      "InitialStack": 1000.0,
      "Stack": 11.0
    }
  ],
  "BotHash": "3C0A986093A124FF7B18D8C5E02F24E9"
}